ether/__init__.py
ether/abi.py
ether/calldata.py
ether/crypto.py
ether/ether_types.py
ether/ethrpc.py
ether/events.py
ether/infura.py
ether/py.typed
ether/rlp.py
ether/transactions.py
ether/tests/__init__.py
ether/tests/helpers.py
ether/tests/test_events.py
riemann_ether-6.0.6.dist-info/LICENSE
riemann_ether-6.0.6.dist-info/METADATA
riemann_ether-6.0.6.dist-info/WHEEL
riemann_ether-6.0.6.dist-info/top_level.txt
riemann_ether-6.0.6.dist-info/RECORD
