Metadata-Version: 2.1
Name: riemann-ether
Version: 6.0.6
Summary: App prototyping library for Ethereum-based chains
Home-page: https://github.com/summa-tx/riemann-ether
Author: James Prestwich
Author-email: james@summa.one
License: UNKNOWN
Keywords: ethereum cryptocurrency blockchain development
Platform: UNKNOWN
Classifier: License :: OSI Approved :: GNU Lesser General Public License v3 (LGPLv3)
Requires-Python: >=3.6
Requires-Dist: eth-keys (==0.3.1)
Requires-Dist: pycryptodomex
Requires-Dist: websockets
